wsaio/__init__.py
wsaio/client.py
wsaio/exceptions.py
wsaio/http.py
wsaio/protocol.py
wsaio/utils.py
wsaio/websocket.py
wsaio-0.0.4.dist-info/LICENSE
wsaio-0.0.4.dist-info/METADATA
wsaio-0.0.4.dist-info/WHEEL
wsaio-0.0.4.dist-info/top_level.txt
wsaio-0.0.4.dist-info/RECORD
