Metadata-Version: 2.1
Name: wsaio
Version: 0.0.4
Summary: An event-driven WebSocket library for Python.
Home-page: https://github.com/asleep-cult/wsaio
Author: asleep-cult
License: UNKNOWN
Platform: UNKNOWN
Classifier: Programming Language :: Python :: 3
Classifier: License :: OSI Approved :: MIT License
Classifier: Operating System :: OS Independent
Requires-Python: >=3.7
